_yapybrot.cp38-win_amd64.pyd
yapybrot/__init__.py
yapybrot/mandelbrot.py
yapybrot-1.0.2.dist-info/LICENSE
yapybrot-1.0.2.dist-info/METADATA
yapybrot-1.0.2.dist-info/WHEEL
yapybrot-1.0.2.dist-info/top_level.txt
yapybrot-1.0.2.dist-info/RECORD
